aleph_vrf/__init__.py
aleph_vrf/exceptions.py
aleph_vrf/models.py
aleph_vrf/settings.py
aleph_vrf/types.py
aleph_vrf/utils.py
aleph_vrf/coordinator/__init__.py
aleph_vrf/coordinator/executor_selection.py
aleph_vrf/coordinator/main.py
aleph_vrf/coordinator/vrf.py
aleph_vrf/executor/__init__.py
aleph_vrf/executor/main.py
aleph_vrf-1.0.0.dist-info/LICENSE.txt
aleph_vrf-1.0.0.dist-info/METADATA
aleph_vrf-1.0.0.dist-info/WHEEL
aleph_vrf-1.0.0.dist-info/top_level.txt
aleph_vrf-1.0.0.dist-info/RECORD
