Metadata-Version: 2.1
Name: aleph-vrf
Version: 1.0.0
Summary: Aleph.im Verifiable Random Function
Home-page: https://github.com/aleph-im/aleph-vrf/
Author: Andres Molins
License: MIT
Project-URL: Documentation, https://github.com/aleph-im/aleph-vrf
Project-URL: Source, https://github.com/aleph-im/aleph-vrf
Platform: any
Classifier: Development Status :: 4 - Beta
Classifier: Programming Language :: Python
License-File: LICENSE.txt
Requires-Dist: aiohttp
Requires-Dist: aleph-sdk-python ==0.7.0
Requires-Dist: hexbytes
Requires-Dist: fastapi >=0.95.1
Requires-Dist: utilitybelt
Requires-Dist: importlib-metadata ; python_version < "3.8"
Provides-Extra: build
Requires-Dist: build ; extra == 'build'
Requires-Dist: twine ; extra == 'build'
Provides-Extra: testing
Requires-Dist: mypy ==1.5.1 ; extra == 'testing'
Requires-Dist: pytest ; extra == 'testing'
Requires-Dist: pytest-asyncio ; extra == 'testing'
Requires-Dist: pytest-cov ; extra == 'testing'
Requires-Dist: pytest-mock ; extra == 'testing'
Requires-Dist: setuptools ; extra == 'testing'
Requires-Dist: uvicorn ; extra == 'testing'
